DirectPayOnline/__init__.py
DirectPayOnline/utils.py
DirectPayOnline/validators.py
DirectPayOnline/xml_templates.py
DirectPayOnline-0.4.dist-info/LICENSE
DirectPayOnline-0.4.dist-info/METADATA
DirectPayOnline-0.4.dist-info/WHEEL
DirectPayOnline-0.4.dist-info/top_level.txt
DirectPayOnline-0.4.dist-info/RECORD
