Metadata-Version: 2.1
Name: DirectPayOnline
Version: 0.4
Summary: A python package to easy the integration with Direct Online Pay (Mpesa, TigoPesa, AirtelMoney, Card Payments)
Home-page: https://github.com/Kalebu/python-dpo
Author: Jordan Kalebu
Author-email: isaackeinstein@gmail.com
License: MIT
Download-URL: https://github.com/Kalebu/python-dpo/archive/refs/tags/v0.2.tar.gz
Keywords: mobile payments,DirectPayOnline(DPO),dpo,payment aggregator,mobile money package
Platform: UNKNOWN
Classifier: Development Status :: 3 - Alpha
Classifier: Intended Audience :: Developers
Classifier: Topic :: Software Development :: Build Tools
Classifier: License :: OSI Approved :: MIT License
Classifier: Programming Language :: Python :: 3.6
Classifier: Programming Language :: Python :: 3.7
Classifier: Programming Language :: Python :: 3.8
Classifier: Programming Language :: Python :: 3.9
Requires-Python: >=3.6
Requires-Dist: requests
Requires-Dist: xmltodict
Requires-Dist: pydantic
